{
  "packageName": "@stackline/ng-multiselect-dropdown",
  "projectRoot": "ng-multiselect-dropdown/ng-multiselect-dropdown",
  "framework": "angular",
  "family": "angular-21",
  "major": 21,
  "exactVersion": "21.2.3",
  "installMode": "npm-install",
  "localInstallSource": "../../../dist-lib",
  "expectedExports": [],
  "installCommand": "npm install --ignore-scripts",
  "validateCommand": "npm run validate",
  "buildCommand": "npm run build:package",
  "generatedAt": "2026-04-08T22:24:23.973Z"
}
